starcat/__init__.py
starcat/bonus.py
starcat-0.0.0.dist-info/LICENSE
starcat-0.0.0.dist-info/METADATA
starcat-0.0.0.dist-info/WHEEL
starcat-0.0.0.dist-info/top_level.txt
starcat-0.0.0.dist-info/RECORD
